vcf2py/__init__.py
vcf2py/vcf.py
vcf2py/tests/__init__.py
vcf2py/tests/test.py
vcf2py-0.2.2.dist-info/LICENSE
vcf2py-0.2.2.dist-info/METADATA
vcf2py-0.2.2.dist-info/WHEEL
vcf2py-0.2.2.dist-info/top_level.txt
vcf2py-0.2.2.dist-info/RECORD
