Metadata-Version: 2.1
Name: vcf2py
Version: 0.2.2
Summary: Tools to process genomic variant data with Numerical Python
Author-email: mikpom <mikpom@mikpom.ru>
Project-URL: Homepage, https://github.com/mikpom/vcf2py
Classifier: Programming Language :: Python :: 3
Classifier: License :: OSI Approved :: MIT License
Classifier: Operating System :: OS Independent
Requires-Python: >=3.7
License-File: LICENSE
Requires-Dist: numpy
Requires-Dist: pysam
